xlsx_validator/__init__.py
xlsx_validator/func.py
xlsx_validator/schemas.py
xlsx_validator-1.0.3.dist-info/LICENSE
xlsx_validator-1.0.3.dist-info/METADATA
xlsx_validator-1.0.3.dist-info/WHEEL
xlsx_validator-1.0.3.dist-info/top_level.txt
xlsx_validator-1.0.3.dist-info/RECORD
