Metadata-Version: 2.1
Name: xlsx_validator
Version: 1.0.3
Summary: Thanks to pydantic, we got a nicer way to extra & validate rows from xslx
Home-page: https://github.com/Pandaaaa906/xlsx_validator
Author: Pandaaaa906
Author-email: ye.pandaaaa906@gmail.com
License: UNKNOWN
Platform: UNKNOWN
License-File: LICENSE
